ollama_ocr/__init__.py
ollama_ocr/app.py
ollama_ocr/ocr_processor.py
ollama_ocr-0.1.6.dist-info/LICENSE
ollama_ocr-0.1.6.dist-info/METADATA
ollama_ocr-0.1.6.dist-info/WHEEL
ollama_ocr-0.1.6.dist-info/top_level.txt
ollama_ocr-0.1.6.dist-info/RECORD
