Metadata-Version: 2.2
Name: ollama-ocr
Version: 0.1.6
Summary: OCR package using Ollama vision language models.
Home-page: https://github.com/imanoop7/Ollama-OCR
Author: Anoop Maurya
Author-email: mauryaanoop3@gmail.com
Classifier: Development Status :: 4 - Beta
Classifier: Intended Audience :: Developers
Classifier: Topic :: Software Development :: Libraries :: Python Modules
Classifier: License :: OSI Approved :: MIT License
Classifier: Programming Language :: Python :: 3
Classifier: Programming Language :: Python :: 3.7
Classifier: Programming Language :: Python :: 3.8
Classifier: Programming Language :: Python :: 3.9
Classifier: Programming Language :: Python :: 3.10
Classifier: Programming Language :: Python :: 3.11
Requires-Python: >=3.7
License-File: LICENSE
Requires-Dist: Pillow
Requires-Dist: requests
Requires-Dist: python-magic
Requires-Dist: transformers
Requires-Dist: streamlit
Requires-Dist: tqdm
Requires-Dist: opencv-python
Requires-Dist: pdf2image
Requires-Dist: numpy
Requires-Dist: pymupdf
Dynamic: author
Dynamic: author-email
Dynamic: classifier
Dynamic: description
Dynamic: description-content-type
Dynamic: home-page
Dynamic: requires-dist
Dynamic: requires-python
Dynamic: summary
